{"note":"This file is an internal implementation detail to speed up HTML report generation. Its format can change at any time. You might be looking for the JSON report: https://coverage.rtfd.io/cmd.html#cmd-json","format":5,"version":"7.6.1","globals":"196ba25a2a7e97a8a746194db9091799","files":{"z_0c9f1d60f1641146___main___py":{"hash":"0007df9a848e26886482f7357cdc4c8c","index":{"url":"z_0c9f1d60f1641146___main___py.html","file":"PyMieSim/__main__.py","description":"","nums":{"precision":0,"n_files":1,"n_statements":9,"n_excluded":0,"n_missing":9,"n_branches":2,"n_partial_branches":0,"n_missing_branches":2}}},"z_8825ae3b34c453d7_base_py":{"hash":"f3f27dc9bc86d99db733f17e59576cd6","index":{"url":"z_8825ae3b34c453d7_base_py.html","file":"PyMieSim/experiment/detector/base.py","description":"","nums":{"precision":0,"n_files":1,"n_statements":56,"n_excluded":0,"n_missing":3,"n_branches":18,"n_partial_branches":6,"n_missing_branches":6}}},"z_8825ae3b34c453d7_coherent_mode_py":{"hash":"358686098f9282a5e60e299de018123e","index":{"url":"z_8825ae3b34c453d7_coherent_mode_py.html","file":"PyMieSim/experiment/detector/coherent_mode.py","description":"","nums":{"precision":0,"n_files":1,"n_statements":20,"n_excluded":0,"n_missing":1,"n_branches":8,"n_partial_branches":2,"n_missing_branches":2}}},"z_8825ae3b34c453d7_photodiode_py":{"hash":"0eae16773a0b793701bdf26d270d194f","index":{"url":"z_8825ae3b34c453d7_photodiode_py.html","file":"PyMieSim/experiment/detector/photodiode.py","description":"","nums":{"precision":0,"n_files":1,"n_statements":13,"n_excluded":0,"n_missing":0,"n_branches":4,"n_partial_branches":0,"n_missing_branches":0}}},"z_35a478f1039d0b90_measure_py":{"hash":"84c9d4f9460db174ac4b0c678ceac433","index":{"url":"z_35a478f1039d0b90_measure_py.html","file":"PyMieSim/experiment/measure.py","description":"","nums":{"precision":0,"n_files":1,"n_statements":37,"n_excluded":0,"n_missing":0,"n_branches":0,"n_partial_branches":0,"n_missing_branches":0}}},"z_35a478f1039d0b90_parameters_py":{"hash":"0551fb149e6e0b5ba731e7c5bf531082","index":{"url":"z_35a478f1039d0b90_parameters_py.html","file":"PyMieSim/experiment/parameters.py","description":"","nums":{"precision":0,"n_files":1,"n_statements":23,"n_excluded":0,"n_missing":0,"n_branches":0,"n_partial_branches":0,"n_missing_branches":0}}},"z_0a2e03dec8aa9585_base_class_py":{"hash":"8db192d65d66b17ba84183f87d116a0f","index":{"url":"z_0a2e03dec8aa9585_base_class_py.html","file":"PyMieSim/experiment/scatterer/base_class.py","description":"","nums":{"precision":0,"n_files":1,"n_statements":43,"n_excluded":0,"n_missing":10,"n_branches":16,"n_partial_branches":2,"n_missing_branches":4}}},"z_0a2e03dec8aa9585_core_shell_py":{"hash":"428de049224c3d1c4639ee2745fe9b75","index":{"url":"z_0a2e03dec8aa9585_core_shell_py.html","file":"PyMieSim/experiment/scatterer/core_shell.py","description":"","nums":{"precision":0,"n_files":1,"n_statements":42,"n_excluded":0,"n_missing":2,"n_branches":12,"n_partial_branches":5,"n_missing_branches":5}}},"z_0a2e03dec8aa9585_cylinder_py":{"hash":"e07bf8ab0a6cc379434c121aa22a6654","index":{"url":"z_0a2e03dec8aa9585_cylinder_py.html","file":"PyMieSim/experiment/scatterer/cylinder.py","description":"","nums":{"precision":0,"n_files":1,"n_statements":38,"n_excluded":0,"n_missing":2,"n_branches":12,"n_partial_branches":5,"n_missing_branches":5}}},"z_0a2e03dec8aa9585_sphere_py":{"hash":"fb69f40ea25a285728ebca2041d54b7c","index":{"url":"z_0a2e03dec8aa9585_sphere_py.html","file":"PyMieSim/experiment/scatterer/sphere.py","description":"","nums":{"precision":0,"n_files":1,"n_statements":38,"n_excluded":0,"n_missing":2,"n_branches":12,"n_partial_branches":5,"n_missing_branches":5}}},"z_35a478f1039d0b90_setup_py":{"hash":"8a9c9cc1eca00dfd0e873c765bec3e54","index":{"url":"z_35a478f1039d0b90_setup_py.html","file":"PyMieSim/experiment/setup.py","description":"","nums":{"precision":0,"n_files":1,"n_statements":97,"n_excluded":0,"n_missing":8,"n_branches":30,"n_partial_branches":3,"n_missing_branches":5}}},"z_4de2cfd94814ac66_base_py":{"hash":"62ed9ed6398bf0fd68a6094eac210cb1","index":{"url":"z_4de2cfd94814ac66_base_py.html","file":"PyMieSim/experiment/source/base.py","description":"","nums":{"precision":0,"n_files":1,"n_statements":35,"n_excluded":0,"n_missing":6,"n_branches":12,"n_partial_branches":3,"n_missing_branches":7}}},"z_4de2cfd94814ac66_gaussian_py":{"hash":"ac48abba660bd4f8b981778cb3ce3f93","index":{"url":"z_4de2cfd94814ac66_gaussian_py.html","file":"PyMieSim/experiment/source/gaussian.py","description":"","nums":{"precision":0,"n_files":1,"n_statements":25,"n_excluded":0,"n_missing":2,"n_branches":12,"n_partial_branches":5,"n_missing_branches":5}}},"z_4de2cfd94814ac66_planewave_py":{"hash":"a416442204ec8f23a8da73016a50d0e3","index":{"url":"z_4de2cfd94814ac66_planewave_py.html","file":"PyMieSim/experiment/source/planewave.py","description":"","nums":{"precision":0,"n_files":1,"n_statements":10,"n_excluded":0,"n_missing":1,"n_branches":2,"n_partial_branches":0,"n_missing_branches":0}}},"z_0c9f1d60f1641146_mesh_py":{"hash":"a4aac1dffb600679d586df15c6af1b15","index":{"url":"z_0c9f1d60f1641146_mesh_py.html","file":"PyMieSim/mesh.py","description":"","nums":{"precision":0,"n_files":1,"n_statements":111,"n_excluded":0,"n_missing":15,"n_branches":28,"n_partial_branches":11,"n_missing_branches":11}}},"z_0c9f1d60f1641146_polarization_py":{"hash":"73cfe14120878b7e98431ba7f7b31993","index":{"url":"z_0c9f1d60f1641146_polarization_py.html","file":"PyMieSim/polarization.py","description":"","nums":{"precision":0,"n_files":1,"n_statements":41,"n_excluded":0,"n_missing":11,"n_branches":10,"n_partial_branches":0,"n_missing_branches":6}}},"z_504aa9835c865e38_detector_py":{"hash":"5d4730f1caf492c955c6e49badb408cf","index":{"url":"z_504aa9835c865e38_detector_py.html","file":"PyMieSim/single/detector.py","description":"","nums":{"precision":0,"n_files":1,"n_statements":129,"n_excluded":0,"n_missing":129,"n_branches":30,"n_partial_branches":0,"n_missing_branches":30}}},"z_631d0f5aae0d4f46_base_py":{"hash":"20cc71af7556b0f2406be85b20b4d01c","index":{"url":"z_631d0f5aae0d4f46_base_py.html","file":"PyMieSim/single/detector/base.py","description":"","nums":{"precision":0,"n_files":1,"n_statements":73,"n_excluded":0,"n_missing":3,"n_branches":14,"n_partial_branches":5,"n_missing_branches":5}}},"z_631d0f5aae0d4f46_coherent_py":{"hash":"4fff389a91ac5b6fbbc45cc43c8b61f8","index":{"url":"z_631d0f5aae0d4f46_coherent_py.html","file":"PyMieSim/single/detector/coherent.py","description":"","nums":{"precision":0,"n_files":1,"n_statements":42,"n_excluded":0,"n_missing":2,"n_branches":12,"n_partial_branches":3,"n_missing_branches":3}}},"z_631d0f5aae0d4f46_uncoherent_py":{"hash":"d55ac815a56d329d831bb8e9974f09e5","index":{"url":"z_631d0f5aae0d4f46_uncoherent_py.html","file":"PyMieSim/single/detector/uncoherent.py","description":"","nums":{"precision":0,"n_files":1,"n_statements":29,"n_excluded":0,"n_missing":0,"n_branches":4,"n_partial_branches":0,"n_missing_branches":0}}},"z_504aa9835c865e38_representations_py":{"hash":"61f358e2a12efd867428f5b9315b0649","index":{"url":"z_504aa9835c865e38_representations_py.html","file":"PyMieSim/single/representations.py","description":"","nums":{"precision":0,"n_files":1,"n_statements":170,"n_excluded":0,"n_missing":4,"n_branches":24,"n_partial_branches":2,"n_missing_branches":2}}},"z_48661ed48dc7ca6c_base_py":{"hash":"ca83512099f36f80aeb1be909984822d","index":{"url":"z_48661ed48dc7ca6c_base_py.html","file":"PyMieSim/single/scatterer/base.py","description":"","nums":{"precision":0,"n_files":1,"n_statements":88,"n_excluded":0,"n_missing":1,"n_branches":40,"n_partial_branches":18,"n_missing_branches":18}}},"z_48661ed48dc7ca6c_core_shell_py":{"hash":"567ec141b70059cb23d623b0bf425046","index":{"url":"z_48661ed48dc7ca6c_core_shell_py.html","file":"PyMieSim/single/scatterer/core_shell.py","description":"","nums":{"precision":0,"n_files":1,"n_statements":49,"n_excluded":0,"n_missing":5,"n_branches":16,"n_partial_branches":7,"n_missing_branches":7}}},"z_48661ed48dc7ca6c_cylinder_py":{"hash":"69b45229ae22fe5bd73029f706bac160","index":{"url":"z_48661ed48dc7ca6c_cylinder_py.html","file":"PyMieSim/single/scatterer/cylinder.py","description":"","nums":{"precision":0,"n_files":1,"n_statements":60,"n_excluded":0,"n_missing":9,"n_branches":24,"n_partial_branches":11,"n_missing_branches":11}}},"z_48661ed48dc7ca6c_sphere_py":{"hash":"0c34221a04cf3e48ddd9c7132b493e06","index":{"url":"z_48661ed48dc7ca6c_sphere_py.html","file":"PyMieSim/single/scatterer/sphere.py","description":"","nums":{"precision":0,"n_files":1,"n_statements":48,"n_excluded":0,"n_missing":7,"n_branches":16,"n_partial_branches":7,"n_missing_branches":7}}},"z_1b2f0c2260893d98_base_py":{"hash":"6d4b0f84f47fcffeca0b25f8dff98323","index":{"url":"z_1b2f0c2260893d98_base_py.html","file":"PyMieSim/single/source/base.py","description":"","nums":{"precision":0,"n_files":1,"n_statements":33,"n_excluded":0,"n_missing":7,"n_branches":24,"n_partial_branches":11,"n_missing_branches":11}}},"z_1b2f0c2260893d98_gaussian_py":{"hash":"e02a93ba638f9683a135acab451f1f1d","index":{"url":"z_1b2f0c2260893d98_gaussian_py.html","file":"PyMieSim/single/source/gaussian.py","description":"","nums":{"precision":0,"n_files":1,"n_statements":33,"n_excluded":0,"n_missing":1,"n_branches":4,"n_partial_branches":1,"n_missing_branches":1}}},"z_1b2f0c2260893d98_planewave_py":{"hash":"1746f161dd015a66850f62cca9de86aa","index":{"url":"z_1b2f0c2260893d98_planewave_py.html","file":"PyMieSim/single/source/planewave.py","description":"","nums":{"precision":0,"n_files":1,"n_statements":26,"n_excluded":0,"n_missing":1,"n_branches":4,"n_partial_branches":1,"n_missing_branches":1}}},"z_0c9f1d60f1641146_special_functions_py":{"hash":"c7ec83094228a6ead592cbeb98b8f4a2","index":{"url":"z_0c9f1d60f1641146_special_functions_py.html","file":"PyMieSim/special_functions.py","description":"","nums":{"precision":0,"n_files":1,"n_statements":49,"n_excluded":0,"n_missing":24,"n_branches":4,"n_partial_branches":0,"n_missing_branches":2}}},"z_0c9f1d60f1641146_units_py":{"hash":"43c0fa829529e205d74b6304020cfced","index":{"url":"z_0c9f1d60f1641146_units_py.html","file":"PyMieSim/units.py","description":"","nums":{"precision":0,"n_files":1,"n_statements":24,"n_excluded":0,"n_missing":0,"n_branches":4,"n_partial_branches":0,"n_missing_branches":0}}},"z_0c9f1d60f1641146_utils_py":{"hash":"b696da97e61499e18726c95b86d2e535","index":{"url":"z_0c9f1d60f1641146_utils_py.html","file":"PyMieSim/utils.py","description":"","nums":{"precision":0,"n_files":1,"n_statements":77,"n_excluded":0,"n_missing":36,"n_branches":20,"n_partial_branches":2,"n_missing_branches":14}}}}}